globrex/__init__.py
globrex-3.1.2.dist-info/METADATA
globrex-3.1.2.dist-info/WHEEL
globrex-3.1.2.dist-info/top_level.txt
globrex-3.1.2.dist-info/RECORD
