Metadata-Version: 2.4
Name: globrex
Version: 3.1.2
Summary: fake globrex executed
Home-page: https://tractusx.dev
Author: kali182
Dynamic: author
Dynamic: home-page
Dynamic: summary
